shpystudy/__init__.py
shpystudy-0.0.7.dist-info/LICENSE
shpystudy-0.0.7.dist-info/METADATA
shpystudy-0.0.7.dist-info/WHEEL
shpystudy-0.0.7.dist-info/top_level.txt
shpystudy-0.0.7.dist-info/RECORD
