Metadata-Version: 2.1
Name: shpystudy
Version: 0.0.7
Summary: a easy package of Shanghai student for easy study
Home-page: UNKNOWN
Author: pvgobserver
Author-email: variflight@feiyou.chat
License: UNKNOWN
Platform: UNKNOWN
Classifier: Programming Language :: Python :: 3
Classifier: License :: OSI Approved :: MIT License
Classifier: Operating System :: OS Independent
Requires-Python: >=3.5
License-File: LICENSE
